exec_sandbox/__init__.py
exec_sandbox/_imports.py
exec_sandbox/_logging.py
exec_sandbox/asset_downloader.py
exec_sandbox/assets.py
exec_sandbox/balloon_client.py
exec_sandbox/cgroup.py
exec_sandbox/cli.py
exec_sandbox/config.py
exec_sandbox/constants.py
exec_sandbox/dns_filter.py
exec_sandbox/exceptions.py
exec_sandbox/guest_agent_protocol.py
exec_sandbox/guest_channel.py
exec_sandbox/gvproxy.py
exec_sandbox/hash_utils.py
exec_sandbox/models.py
exec_sandbox/overlay_pool.py
exec_sandbox/package_validator.py
exec_sandbox/permission_utils.py
exec_sandbox/platform_utils.py
exec_sandbox/port_forward.py
exec_sandbox/process_registry.py
exec_sandbox/py.typed
exec_sandbox/qemu_cmd.py
exec_sandbox/qemu_storage_daemon.py
exec_sandbox/qemu_vm.py
exec_sandbox/resource_cleanup.py
exec_sandbox/scheduler.py
exec_sandbox/settings.py
exec_sandbox/snapshot_manager.py
exec_sandbox/socket_auth.py
exec_sandbox/subprocess_utils.py
exec_sandbox/system_probes.py
exec_sandbox/validation.py
exec_sandbox/vm_manager.py
exec_sandbox/vm_timing.py
exec_sandbox/vm_types.py
exec_sandbox/vm_working_directory.py
exec_sandbox/warm_vm_pool.py
exec_sandbox/resources/npm_top_10k.json
exec_sandbox/resources/pypi_top_10k.json
exec_sandbox-0.8.0.dist-info/METADATA
exec_sandbox-0.8.0.dist-info/WHEEL
exec_sandbox-0.8.0.dist-info/entry_points.txt
exec_sandbox-0.8.0.dist-info/licenses/LICENSE
exec_sandbox-0.8.0.dist-info/RECORD
