Metadata-Version: 2.4
Name: exec-sandbox
Version: 0.8.0
Summary: Secure code execution in microVMs with QEMU
Project-URL: Homepage, https://github.com/dualeai/exec-sandbox
Project-URL: Documentation, https://github.com/dualeai/exec-sandbox#readme
Project-URL: Repository, https://github.com/dualeai/exec-sandbox.git
Project-URL: Changelog, https://github.com/dualeai/exec-sandbox/releases
Project-URL: Issues, https://github.com/dualeai/exec-sandbox/issues
Author-email: Duale AI <hello@duale.ai>
License-Expression: Apache-2.0
License-File: LICENSE
Keywords: code-execution,isolation,microvm,qemu,sandbox,security,virtualization,vm
Classifier: Development Status :: 4 - Beta
Classifier: Intended Audience :: Developers
Classifier: License :: OSI Approved :: Apache Software License
Classifier: Operating System :: MacOS
Classifier: Operating System :: POSIX :: Linux
Classifier: Programming Language :: Python :: 3
Classifier: Programming Language :: Python :: 3.12
Classifier: Programming Language :: Python :: 3.13
Classifier: Programming Language :: Python :: 3.14
Classifier: Programming Language :: Python :: Implementation :: CPython
Classifier: Topic :: Security
Classifier: Topic :: Software Development :: Interpreters
Classifier: Typing :: Typed
Requires-Python: >=3.12
Requires-Dist: aiofiles~=24.0
Requires-Dist: aiohttp~=3.11
Requires-Dist: aiojobs~=1.3
Requires-Dist: backports-zstd; python_version < '3.14'
Requires-Dist: click~=8.0
Requires-Dist: psutil~=7.2
Requires-Dist: pydantic-settings~=2.0
Requires-Dist: pydantic~=2.0
Requires-Dist: qemu-qmp~=0.0.5
Requires-Dist: tenacity~=8.0
Provides-Extra: dev
Requires-Dist: aioresponses~=0.7; extra == 'dev'
Requires-Dist: hypothesis~=6.0; extra == 'dev'
Requires-Dist: moto[s3,server]~=5.0; extra == 'dev'
Requires-Dist: py-spy~=0.4; extra == 'dev'
Requires-Dist: pyright~=1.1; extra == 'dev'
Requires-Dist: pytest-asyncio~=0.24; extra == 'dev'
Requires-Dist: pytest-cov~=6.0; extra == 'dev'
Requires-Dist: pytest-timeout~=2.3; extra == 'dev'
Requires-Dist: pytest-xdist~=3.5; extra == 'dev'
Requires-Dist: pytest~=8.0; extra == 'dev'
Requires-Dist: ruff~=0.7; extra == 'dev'
Requires-Dist: twine~=6.1; extra == 'dev'
Requires-Dist: vulture~=2.14; extra == 'dev'
Provides-Extra: s3
Requires-Dist: aioboto3~=13.0; extra == 's3'
